bild/__init__.py
bild/amis.py
bild/core.py
bild/cython_imports.py
bild/models.py
bild/postproc.py
bild/stats.py
bild/util.py
bild/src/MSRouse_logL.c
bild/src/MSRouse_logL_py.py
bild-0.0.5.dist-info/LICENSE
bild-0.0.5.dist-info/METADATA
bild-0.0.5.dist-info/WHEEL
bild-0.0.5.dist-info/top_level.txt
bild-0.0.5.dist-info/RECORD
