Metadata-Version: 2.1
Name: bild
Version: 0.0.5
Summary: Bayesian Inference of Looping Dynamics
Author-email: Simon Grosse-Holz <sgh256@mit.edu>
License: MIT License
Project-URL: Homepage, https://github.com/OpenTrajectoryAnalysis/bild
Project-URL: Documentation, https://bild.readthedocs.org/en/latest
Project-URL: Bug Tracker, https://github.com/OpenTrajectoryAnalysis/bild/issues
Classifier: Programming Language :: Python :: 3
Classifier: License :: OSI Approved :: MIT License
Classifier: Operating System :: OS Independent
Requires-Python: >=3.7
License-File: LICENSE
Requires-Dist: noctiluca (>=0)
Requires-Dist: rouse (>=0)
Requires-Dist: numpy (>=1.20)
Requires-Dist: scipy (>=1.6)
Requires-Dist: tqdm (>=4)
